{
  "schemaVersion": "1.0.0",
  "snapshotId": "2026-07",
  "generatedAt": "2026-07-23T22:15:22.691Z",
  "generatedAtKst": "2026. 7. 24. AM 7:15:22",
  "period": {
    "startDate": "2026-07-01",
    "endDate": "2026-07-31",
    "timezone": "Asia/Seoul"
  },
  "source": {
    "provider": "data.go.kr",
    "apiName": "abandonmentPublicService_v2",
    "sourceType": "public-data-api"
  },
  "dataBoundary": {
    "isLiveData": false,
    "isPublicSafe": true,
    "containsSecrets": false,
    "containsFullUpstreamUrl": false
  },
  "collection": {
    "state": "notice",
    "numOfRows": 1000,
    "maxPages": 10,
    "pagesFetched": 3,
    "upstreamTotalCount": 2351,
    "truncated": false,
    "responseFormat": "json"
  },
  "counts": {
    "itemCount": 2351,
    "normalizedItemCount": 2351,
    "currentCount": 2351,
    "urgentCount": 835,
    "protectedCount": 2351,
    "archiveCount": 0,
    "eventCount": 1338,
    "missingRecordCount": 2320,
    "timelineNoticeCount": 4662,
    "timelineEventCount": 8849
  },
  "freshnessRules": {
    "dateField": "noticeEdt",
    "currentRule": "noticeEdt is valid and not expired at Asia/Seoul date",
    "urgentRule": "days_left is between 0 and 3",
    "timezone": "Asia/Seoul"
  },
  "files": {
    "snapshotJson": "app/public/data/monthly-notices/2026-07.json",
    "snapshotMetaJson": "app/public/data/monthly-notices/2026-07.meta.json",
    "latestJson": "app/public/data/latest-notices.json",
    "latestMetaJson": "app/public/data/latest-notices.meta.json",
    "dailyEventsJson": "app/public/data/daily-events/2026-07-24.json",
    "latestEventsJson": "app/public/data/latest-events.json",
    "missingNoticesJson": "app/public/data/missing-notices.json",
    "noticeTimelinesJson": "app/public/data/notice-timelines.json"
  },
  "warnings": [],
  "claimBoundary": [
    "monthly public-data snapshot",
    "not real-time notice service",
    "not complete upstream-data guarantee",
    "not shelter operation data",
    "not adoption outcome tracking",
    "collector-observed change events",
    "missing observations do not prove a final animal outcome"
  ],
  "runtime": {
    "durationMs": 24100
  },
  "changeEvents": {
    "schemaVersion": "1.0.0",
    "observationDate": "2026-07-24",
    "baseline": false,
    "observationWindowChanged": false,
    "summary": {
      "NEW": 343,
      "DEADLINE_CHANGED": 0,
      "STATUS_CHANGED": 0,
      "BECAME_URGENT": 584,
      "NOT_OBSERVED": 280,
      "DISAPPEARED": 131,
      "RETURNED": 0,
      "total": 1338
    }
  },
  "noticeTimelines": {
    "schemaVersion": "1.0.0",
    "updatedAt": "2026-07-23T22:15:22.691Z",
    "latestObservationDate": "2026-07-24",
    "noticeCount": 4662,
    "eventCount": 8849
  }
}
